isage_anns-0.1.3.dist-info/licenses/LICENSE
sage_anns/PyCANDYAlgo.cpython-310-x86_64-linux-gnu.so
sage_anns/__init__.py
sage_anns/base.py
sage_anns/factory.py
sage_anns/py.typed
sage_anns/algorithms/__init__.py
sage_anns/algorithms/gti_wrapper.py
sage_anns/algorithms/plsh_wrapper.py
sage_anns/algorithms/pycandy_wrapper.py
sage_anns/algorithms/vsag_wrapper.py
sage_anns/algorithms/candy/__init__.py
sage_anns/algorithms/candy/base.py
sage_anns/algorithms/candy/diskann.py
sage_anns/algorithms/candy/dpg.py
sage_anns/algorithms/candy/faiss_wrapper.py
sage_anns/algorithms/candy/flat.py
sage_anns/algorithms/candy/lshapg.py
sage_anns/algorithms/candy/nndescent.py
sage_anns/algorithms/candy/onlinepq.py
sage_anns/algorithms/candy/sptag.py
sage_anns/algorithms/candy/utils.py
isage_anns-0.1.3.dist-info/METADATA
isage_anns-0.1.3.dist-info/WHEEL
isage_anns-0.1.3.dist-info/RECORD
