Metadata-Version: 2.2
Name: isage-anns
Version: 0.1.3
Summary: SAGE ANNS: Approximate Nearest Neighbor Search algorithms with unified Python interface
Keywords: approximate nearest neighbor,anns,vector search,similarity search,faiss,hnsw,diskann
Author-Email: IntelliStream Team <shuhao_zhang@hust.edu.cn>
License: MIT
Classifier: Development Status :: 4 - Beta
Classifier: Intended Audience :: Developers
Classifier: Intended Audience :: Science/Research
Classifier: Topic :: Scientific/Engineering :: Artificial Intelligence
Classifier: Topic :: Scientific/Engineering :: Information Analysis
Classifier: Programming Language :: C++
Classifier: Programming Language :: Python :: 3
Classifier: Programming Language :: Python :: 3.10
Classifier: Programming Language :: Python :: 3.11
Classifier: Programming Language :: Python :: 3.12
Project-URL: Homepage, https://github.com/intellistream/sage-anns
Project-URL: Repository, https://github.com/intellistream/sage-anns.git
Project-URL: Bug Tracker, https://github.com/intellistream/sage-anns/issues
Project-URL: Documentation, https://github.com/intellistream/sage-anns#readme
Requires-Python: >=3.10
Requires-Dist: numpy>=1.20.0
Requires-Dist: pybind11>=2.10.0
